{
    "parent": "djzc444:fight/count_kill10",
    "display": {
        "icon": {
            "id": "minecraft:netherite_axe"
        },
        "title": {
            "translate": "djzc.advancement.count_kill30",
            "fallback":"核子危机"
        },
        "description": {
            "translate": "djzc.advancement.count_kill30.desc",
            "fallback": "一局内取得30杀"
        },
        "frame": "task",
        "show_toast": false,
        "announce_to_chat":true,
        "hidden": true
    },
    "criteria": {
        "basic": {
            "trigger": "minecraft:impossible"

        }
    },
    "requirements": [
        ["basic"]
    ]
}